[
  {
    "Name": "test",
    "ScanDir": "C:\\b",
    "EndDir": "C:\\a",
    "Extensions": [
      {
        "Name": "Audio",
        "Endings": [
          ".mp3",
          ".wav"
        ]
      },
      {
        "Name": "Textfile",
        "Endings": [
          ".txt",
          ".json"
        ]
      },
      {
        "Name": "Ordner",
        "Endings": []
      },
      {
        "Name": "Rest",
        "Endings": []
      }
    ],
    "StaticDirs": [
      "C:\\a\\trash"
    ],
    "DeleteFromDesktop": false,
    "SortByYearMonth": false,
    "LinuxOS": false
  }
]